llama_index/embeddings/heroku/__init__.py
llama_index/embeddings/heroku/base.py
llama_index_embeddings_heroku-0.1.1.dist-info/METADATA
llama_index_embeddings_heroku-0.1.1.dist-info/WHEEL
llama_index_embeddings_heroku-0.1.1.dist-info/licenses/LICENSE
llama_index_embeddings_heroku-0.1.1.dist-info/RECORD
