Metadata-Version: 2.4
Name: llama-index-embeddings-heroku
Version: 0.1.1
Summary: llama-index embeddings heroku managed inference integration
Author-email: LlamaIndex <dev@llamaindex.ai>
License-Expression: MIT
License-File: LICENSE
Requires-Python: <4.0,>=3.9
Requires-Dist: httpx>=0.24.0
Requires-Dist: llama-index-core<0.15,>=0.13.0
